transiter/__init__.py
transiter/__metadata__.py
transiter/clt.py
transiter/config.py
transiter/exceptions.py
transiter/db/__init__.py
transiter/db/dbconnection.py
transiter/db/alembic/__init__.py
transiter/db/alembic/env.py
transiter/db/alembic/versions/055583d82811_add_system_update_table.py
transiter/db/alembic/versions/08ce9c5194a4_add_extra_columns_to_stop_table.py
transiter/db/alembic/versions/123df9e95dda_add_some_db_constraints.py
transiter/db/alembic/versions/14fa42915420_initial_database_setup.py
transiter/db/alembic/versions/1e99b5efb76f_add_vehicle_table.py
transiter/db/alembic/versions/29e3a1cc76da_changes_to_the_trip_table.py
transiter/db/alembic/versions/2bbd670f53b4_add_full_alerts_support.py
transiter/db/alembic/versions/36e00f5e2f0e_add_scheduled_service_exceptions.py
transiter/db/alembic/versions/423495a41dd6_db_changes_for_system_config_updates.py
transiter/db/alembic/versions/455692a5a808_add_transfers_config_table.py
transiter/db/alembic/versions/4b61fb4aef27_add_extra_gtfs_static_fields_to_route_.py
transiter/db/alembic/versions/5bc1207e7593_make_enum_non_native.py
transiter/db/alembic/versions/65146f234144_add_system_auto_update_enabled_field.py
transiter/db/alembic/versions/65551af9cd46_add_transfers_table.py
transiter/db/alembic/versions/8068ba0ab781_add_non_null_source_contraints.py
transiter/db/alembic/versions/9f99961cd677_add_agency_table.py
transiter/db/alembic/versions/__init__.py
transiter/db/alembic/versions/b521e2a9055a_feed_update_auditing.py
transiter/db/alembic/versions/be93cf805bb4_add_trip_stop_time_future_non_null_.py
transiter/db/alembic/versions/f722a8952973_feed_update_aggregation_index.py
transiter/db/models/__init__.py
transiter/db/models/agency.py
transiter/db/models/alert.py
transiter/db/models/alertactiveperiod.py
transiter/db/models/alertmessage.py
transiter/db/models/base.py
transiter/db/models/directionrule.py
transiter/db/models/feed.py
transiter/db/models/feedupdate.py
transiter/db/models/route.py
transiter-0.5.5.dist-info/METADATA
transiter-0.5.5.dist-info/WHEEL
transiter-0.5.5.dist-info/entry_points.txt
transiter-0.5.5.dist-info/top_level.txt
transiter-0.5.5.dist-info/RECORD
