Metadata-Version: 2.1
Name: transiter
Version: 0.5.5
Summary: HTTP web service for transit data
Home-page: https://github.com/jamespfennell/transiter
Author: James Fennell
Author-email: jamespfennell@gmail.com
License: MIT
Platform: UNKNOWN
Requires-Dist: alembic (==1.4.2)
Requires-Dist: apscheduler (==3.6.3)
Requires-Dist: celery (==4.4.2)
Requires-Dist: click (==7.1.1)
Requires-Dist: decorator (==4.4.2)
Requires-Dist: flask (==1.1.2)
Requires-Dist: gunicorn (==20.0.4)
Requires-Dist: inflection (==0.4.0)
Requires-Dist: Jinja2 (==2.11.2)
Requires-Dist: prometheus-client (==0.9.0)
Requires-Dist: protobuf (==3.11.3)
Requires-Dist: psycopg2-binary (==2.8.5)
Requires-Dist: pytimeparse (==1.1.8)
Requires-Dist: pytz (==2019.3)
Requires-Dist: requests (==2.23.0)
Requires-Dist: sqlalchemy (==1.3.16)
Requires-Dist: strictyaml (==1.0.6)
